parseable_dataclasses/__init__.py
parseable_dataclasses/mixin.py
parseable_dataclasses/py.typed
parseable_dataclasses-1.0.0.dist-info/METADATA
parseable_dataclasses-1.0.0.dist-info/WHEEL
parseable_dataclasses-1.0.0.dist-info/RECORD
