Metadata-Version: 2.4
Name: parseable-dataclasses
Version: 1.0.0
Summary: Dataclass extension to use argparse
License-Expression: MIT
Requires-Python: >=3.12
